<builds>
<build>
<name>[COLOR dodgerblue]---- Kodibox Builds ----[/COLOR]</name>
<kodi>K21</kodi>
<url>http://</url>
<icon>https://dr-venture.com/709/Artwork/709_Icon.jpg</icon>
<fanart>https://dr-venture.com/709/Artwork/709Wizard-Fanart.jpg</fanart>
<description>by XxAttackerxX</description>
</build>
<build>
<name>KodiBox</name>
<version>1.0</version>
<kodi>K21</kodi>
<size>78MB</size>
<url>https://github.com/kodibox32/kodibox/releases/download/Kodibox/kodibox.zip</url>
<icon>https://dr-venture.com/709/Artwork/709Xlite_Lite_Icon.jpg</icon>
<fanart>https://dr-venture.com/709/Artwork/709Wizard-Fanart.jpg</fanart>
<description>A light build with an easy-to-navigate interface - Debrid Only - Updated Oct 29-2025</description>
</build>
</builds>
